blizzardapi/__init__.py
blizzardapi/api.py
blizzardapi/blizzard_api.py
blizzardapi/battlenet/__init__.py
blizzardapi/battlenet/battlenet_api.py
blizzardapi/battlenet/battlenet_oauth_api.py
blizzardapi/diablo3/__init__.py
blizzardapi/diablo3/diablo3_api.py
blizzardapi/diablo3/diablo3_community_api.py
blizzardapi/diablo3/diablo3_game_data_api.py
blizzardapi/hearthstone/__init__.py
blizzardapi/hearthstone/hearthstone_api.py
blizzardapi/hearthstone/hearthstone_game_data_api.py
blizzardapi/wow/__init__.py
blizzardapi/wow/wow_api.py
blizzardapi/wow/wow_game_data_api.py
blizzardapi/wow/wow_profile_api.py
tests/__init__.py
tests/conftest.py
tests/fixtures.py
tests/test_battlenet_oauth_api.py
tests/test_diablo3_community_api.py
tests/test_diablo3_game_data_api.py
tests/test_hearthstone_game_data_api.py
tests/test_wow_classic_game_data_api.py
tests/test_wow_game_data_api.py
tests/test_wow_profile_api.py
python_blizzardapi-1.3.0.dist-info/LICENSE
python_blizzardapi-1.3.0.dist-info/METADATA
python_blizzardapi-1.3.0.dist-info/WHEEL
python_blizzardapi-1.3.0.dist-info/top_level.txt
python_blizzardapi-1.3.0.dist-info/RECORD
